rabbitmqrun/__init__.py
rabbitmqrun/cli.py
rabbitmqrun-0.1.1.dist-info/entry_points.txt
rabbitmqrun-0.1.1.dist-info/WHEEL
rabbitmqrun-0.1.1.dist-info/METADATA
rabbitmqrun-0.1.1.dist-info/RECORD
